topex/__init__.py
topex/_nbdev.py
topex/core.py
topex/internal.py
topex/preprocessing.py
topex-0.1.1.dist-info/LICENSE
topex-0.1.1.dist-info/METADATA
topex-0.1.1.dist-info/WHEEL
topex-0.1.1.dist-info/entry_points.txt
topex-0.1.1.dist-info/top_level.txt
topex-0.1.1.dist-info/RECORD
